togai_my_package-0.0.9.dist-info/licenses/LICENSE.txt
togai_my_packaging/__init__.py
togai_my_packaging/my_file.py
togai_my_packaging/my_other_file.py
togai_my_packaging/states_info.py
togai_my_packaging/my_folder/__init__.py
togai_my_packaging/my_folder/my_nested_file.py
togai_my_package-0.0.9.dist-info/METADATA
togai_my_package-0.0.9.dist-info/WHEEL
togai_my_package-0.0.9.dist-info/top_level.txt
togai_my_package-0.0.9.dist-info/RECORD
